addone/__init__.py
addone/main.py
zrjaddone-1.0.0.dist-info/LICENSE.txt
zrjaddone-1.0.0.dist-info/METADATA
zrjaddone-1.0.0.dist-info/WHEEL
zrjaddone-1.0.0.dist-info/entry_points.txt
zrjaddone-1.0.0.dist-info/top_level.txt
zrjaddone-1.0.0.dist-info/RECORD
